pytest_smell/__init__.py
pytest_smell/__main__.py
pytest_smell/config.py
pytest_smell/constants.py
pytest_smell/parser.py
pytest_smell/processing.py
pytest_smell/smells.py
pytest_smell/utils.py
pytest_smell-1.0.5.dist-info/METADATA
pytest_smell-1.0.5.dist-info/WHEEL
pytest_smell-1.0.5.dist-info/entry_points.txt
pytest_smell-1.0.5.dist-info/top_level.txt
pytest_smell-1.0.5.dist-info/RECORD
