Metadata-Version: 2.1
Name: pytest-smell
Version: 1.0.5
Summary: Automated bad smell detection tool for Pytest
Home-page: https://github.com/maxpacs98/disertation
Author: Bodea Alex
Author-email: alexandrubodeag@gmail.com
License: MIT
Classifier: License :: OSI Approved :: MIT License
Classifier: Programming Language :: Python :: 3
Classifier: Programming Language :: Python :: 3.9
